{
  "id": 141,
  "versao": 1,
  "data": "2026-01-04",
  "dificuldade": "Fácil",
  "tema": "Café da manhã",
  "cols": 11,
  "rows": 11,
  "grid": [
    "",
    "G",
    "",
    "",
    "",
    "",
    "",
    "L",
    "",
    "",
    "M",
    "",
    "E",
    "",
    "M",
    "A",
    "N",
    "T",
    "E",
    "I",
    "G",
    "A",
    "",
    "L",
    "",
    "",
    "",
    "",
    "",
    "I",
    "",
    "",
    "N",
    "",
    "E",
    "",
    "",
    "",
    "F",
    "",
    "T",
    "",
    "",
    "T",
    "",
    "I",
    "O",
    "G",
    "U",
    "R",
    "T",
    "E",
    "",
    "",
    "E",
    "",
    "A",
    "",
    "",
    "",
    "U",
    "",
    "",
    "",
    "",
    "I",
    "",
    "",
    "",
    "F",
    "",
    "T",
    "",
    "",
    "",
    "",
    "G",
    "",
    "C",
    "E",
    "R",
    "E",
    "A",
    "I",
    "S",
    "",
    "",
    "A",
    "",
    "",
    "",
    "I",
    "",
    "S",
    "",
    "U",
    "",
    "",
    "",
    "",
    "",
    "",
    "O",
    "",
    "",
    "",
    "C",
    "A",
    "F",
    "É",
    "P",
    "Ã",
    "E",
    "S",
    "",
    "",
    "",
    "O",
    "",
    "",
    ""
  ],
  "words": [
    {
      "word": "GELEIA",
      "positions": [
        1,
        12,
        23,
        34,
        45,
        56
      ]
    },
    {
      "word": "IOGURTE",
      "positions": [
        45,
        46,
        47,
        48,
        49,
        50,
        51
      ]
    },
    {
      "word": "FRUTAS",
      "positions": [
        38,
        49,
        60,
        71,
        82,
        93
      ]
    },
    {
      "word": "CEREAIS",
      "positions": [
        78,
        79,
        80,
        81,
        82,
        83,
        84
      ]
    },
    {
      "word": "FRIOS",
      "positions": [
        69,
        80,
        91,
        102,
        113
      ]
    },
    {
      "word": "PÃES",
      "positions": [
        110,
        111,
        112,
        113
      ]
    },
    {
      "word": "MANTEIGA",
      "positions": [
        14,
        15,
        16,
        17,
        18,
        19,
        20,
        21
      ]
    },
    {
      "word": "LEITE",
      "positions": [
        7,
        18,
        29,
        40,
        51
      ]
    },
    {
      "word": "MANTEIGA",
      "positions": [
        10,
        21,
        32,
        43,
        54,
        65,
        76,
        87
      ]
    },
    {
      "word": "SUCO",
      "positions": [
        84,
        95,
        106,
        117
      ]
    },
    {
      "word": "CAFÉ",
      "positions": [
        106,
        107,
        108,
        109
      ]
    }
  ]
}