{
  "id": 16,
  "versao": 3,
  "data": "2025-08-24",
  "dificuldade": "Difícil",
  "tema": "",
  "cols": 9,
  "rows": 9,
  "grid": [
    "",
    "",
    "",
    "",
    "",
    "",
    "",
    "",
    "",
    "",
    "",
    "",
    "",
    "",
    "",
    "",
    "",
    "",
    "",
    "F",
    "F",
    "F",
    "",
    "F",
    "F",
    "F",
    "",
    "",
    "F",
    "",
    "",
    "",
    "F",
    "",
    "",
    "",
    "",
    "F",
    "F",
    "F",
    "",
    "F",
    "",
    "",
    "",
    "",
    "F",
    "",
    "",
    "",
    "F",
    "",
    "",
    "",
    "",
    "F",
    "",
    "",
    "",
    "F",
    "F",
    "F",
    "",
    "",
    "",
    "",
    "",
    "",
    "",
    "",
    "",
    "",
    "",
    "",
    "",
    "",
    "",
    "",
    "",
    "",
    ""
  ],
  "words": [
    {
      "word": "FC",
      "positions": [
        19,
        20,
        21,
        23,
        24,
        25,
        28,
        32,
        37,
        38,
        39,
        41,
        46,
        50,
        55,
        59,
        60,
        61
      ]
    }
  ]
}