{
  "id": 163,
  "versao": 1,
  "data": "2026-01-26",
  "dificuldade": "Fácil",
  "tema": "Ações em redes sociais",
  "cols": 11,
  "rows": 12,
  "grid": [
    "P",
    "U",
    "B",
    "L",
    "I",
    "C",
    "A",
    "R",
    "",
    "",
    "",
    "",
    "",
    "",
    "",
    "",
    "O",
    "",
    "",
    "",
    "",
    "",
    "",
    "",
    "",
    "",
    "",
    "M",
    "A",
    "R",
    "C",
    "A",
    "R",
    "",
    "",
    "",
    "",
    "",
    "P",
    "",
    "",
    "",
    "",
    "",
    "",
    "",
    "C",
    "",
    "S",
    "A",
    "L",
    "V",
    "A",
    "R",
    "",
    "",
    "",
    "O",
    "",
    "",
    "R",
    "",
    "",
    "",
    "",
    "",
    "",
    "",
    "M",
    "",
    "",
    "T",
    "",
    "",
    "",
    "",
    "",
    "",
    "S",
    "E",
    "G",
    "U",
    "I",
    "R",
    "",
    "",
    "",
    "",
    "",
    "",
    "N",
    "",
    "",
    "L",
    "",
    "",
    "",
    "",
    "",
    "",
    "",
    "T",
    "",
    "",
    "H",
    "",
    "",
    "",
    "",
    "",
    "",
    "",
    "A",
    "",
    "",
    "A",
    "",
    "",
    "",
    "",
    "",
    "C",
    "U",
    "R",
    "T",
    "I",
    "R",
    "",
    "",
    "",
    "",
    ""
  ],
  "words": [
    {
      "word": "PUBLICAR",
      "positions": [
        0,
        1,
        2,
        3,
        4,
        5,
        6,
        7
      ]
    },
    {
      "word": "COMPARTILHAR",
      "positions": [
        5,
        16,
        27,
        38,
        49,
        60,
        71,
        82,
        93,
        104,
        115,
        126
      ]
    },
    {
      "word": "MARCAR",
      "positions": [
        27,
        28,
        29,
        30,
        31,
        32
      ]
    },
    {
      "word": "SALVAR",
      "positions": [
        48,
        49,
        50,
        51,
        52,
        53
      ]
    },
    {
      "word": "COMENTAR",
      "positions": [
        46,
        57,
        68,
        79,
        90,
        101,
        112,
        123
      ]
    },
    {
      "word": "CURTIR",
      "positions": [
        121,
        122,
        123,
        124,
        125,
        126
      ]
    },
    {
      "word": "SEGUIR",
      "positions": [
        78,
        79,
        80,
        81,
        82,
        83
      ]
    }
  ]
}