{
  "id": 174,
  "versao": 1,
  "data": "2026-02-06",
  "dificuldade": "Fácil",
  "tema": "Abertura de Jogos Olímpicos",
  "cols": 10,
  "rows": 11,
  "grid": [
    "P",
    "",
    "",
    "",
    "",
    "",
    "",
    "",
    "",
    "",
    "I",
    "",
    "D",
    "E",
    "S",
    "F",
    "I",
    "L",
    "E",
    "",
    "R",
    "",
    "E",
    "",
    "",
    "",
    "",
    "",
    "",
    "",
    "A",
    "T",
    "L",
    "E",
    "T",
    "A",
    "S",
    "",
    "",
    "",
    "",
    "",
    "E",
    "",
    "",
    "",
    "",
    "",
    "",
    "",
    "",
    "",
    "G",
    "",
    "",
    "",
    "H",
    "",
    "",
    "",
    "",
    "B",
    "A",
    "N",
    "D",
    "E",
    "I",
    "R",
    "A",
    "S",
    "",
    "",
    "Ç",
    "",
    "",
    "",
    "N",
    "",
    "",
    "",
    "",
    "",
    "Õ",
    "",
    "",
    "T",
    "O",
    "C",
    "H",
    "A",
    "",
    "",
    "E",
    "",
    "",
    "",
    "",
    "",
    "",
    "",
    "",
    "E",
    "S",
    "T",
    "Á",
    "D",
    "I",
    "O",
    "",
    ""
  ],
  "words": [
    {
      "word": "PIRA",
      "positions": [
        0,
        10,
        20,
        30
      ]
    },
    {
      "word": "ATLETAS",
      "positions": [
        30,
        31,
        32,
        33,
        34,
        35,
        36
      ]
    },
    {
      "word": "DELEGAÇÕES",
      "positions": [
        12,
        22,
        32,
        42,
        52,
        62,
        72,
        82,
        92,
        102
      ]
    },
    {
      "word": "ESTÁDIO",
      "positions": [
        101,
        102,
        103,
        104,
        105,
        106,
        107
      ]
    },
    {
      "word": "BANDEIRAS",
      "positions": [
        61,
        62,
        63,
        64,
        65,
        66,
        67,
        68,
        69
      ]
    },
    {
      "word": "DESFILE",
      "positions": [
        12,
        13,
        14,
        15,
        16,
        17,
        18
      ]
    },
    {
      "word": "HINO",
      "positions": [
        56,
        66,
        76,
        86
      ]
    },
    {
      "word": "TOCHA",
      "positions": [
        85,
        86,
        87,
        88,
        89
      ]
    }
  ]
}