{
  "id": 207,
  "versao": 1,
  "data": "2026-03-11",
  "dificuldade": "Fácil",
  "tema": "Planetas do sistema solar",
  "cols": 10,
  "rows": 11,
  "grid": [
    "",
    "",
    "",
    "",
    "",
    "",
    "",
    "M",
    "",
    "",
    "",
    "",
    "",
    "",
    "",
    "J",
    "",
    "E",
    "",
    "",
    "",
    "",
    "",
    "",
    "",
    "Ú",
    "",
    "R",
    "",
    "",
    "",
    "V",
    "",
    "",
    "",
    "P",
    "",
    "C",
    "",
    "",
    "",
    "Ê",
    "",
    "",
    "",
    "I",
    "",
    "Ú",
    "",
    "M",
    "",
    "N",
    "",
    "N",
    "",
    "T",
    "E",
    "R",
    "R",
    "A",
    "",
    "U",
    "",
    "E",
    "",
    "E",
    "",
    "I",
    "",
    "R",
    "",
    "S",
    "A",
    "T",
    "U",
    "R",
    "N",
    "O",
    "",
    "T",
    "",
    "",
    "",
    "U",
    "",
    "",
    "",
    "",
    "",
    "E",
    "U",
    "R",
    "A",
    "N",
    "O",
    "",
    "",
    "",
    "",
    "",
    "",
    "",
    "",
    "O",
    "",
    "",
    "",
    "",
    "",
    ""
  ],
  "words": [
    {
      "word": "URANO",
      "positions": [
        90,
        91,
        92,
        93,
        94
      ]
    },
    {
      "word": "NETUNO",
      "positions": [
        53,
        63,
        73,
        83,
        93,
        103
      ]
    },
    {
      "word": "SATURNO",
      "positions": [
        71,
        72,
        73,
        74,
        75,
        76,
        77
      ]
    },
    {
      "word": "VÊNUS",
      "positions": [
        31,
        41,
        51,
        61,
        71
      ]
    },
    {
      "word": "JÚPITER",
      "positions": [
        15,
        25,
        35,
        45,
        55,
        65,
        75
      ]
    },
    {
      "word": "MERCÚRIO",
      "positions": [
        7,
        17,
        27,
        37,
        47,
        57,
        67,
        77
      ]
    },
    {
      "word": "TERRA",
      "positions": [
        55,
        56,
        57,
        58,
        59
      ]
    },
    {
      "word": "MARTE",
      "positions": [
        49,
        59,
        69,
        79,
        89
      ]
    }
  ]
}