{
  "id": 323,
  "versao": 1,
  "data": "2026-07-05",
  "dificuldade": "Difícil",
  "tema": "Noruega",
  "cols": 13,
  "rows": 17,
  "grid": [
    "",
    "",
    "",
    "",
    "",
    "",
    "",
    "",
    "",
    "",
    "",
    "V",
    "",
    "",
    "",
    "",
    "",
    "",
    "",
    "",
    "",
    "",
    "",
    "",
    "A",
    "",
    "",
    "H",
    "",
    "",
    "",
    "",
    "",
    "",
    "O",
    "",
    "",
    "L",
    "",
    "P",
    "A",
    "Í",
    "S",
    "+",
    "N",
    "Ó",
    "R",
    "D",
    "I",
    "C",
    "O",
    "",
    "",
    "A",
    "",
    "",
    "",
    "",
    "",
    "",
    "E",
    "",
    "",
    "R",
    "",
    "",
    "L",
    "",
    "V",
    "I",
    "K",
    "I",
    "N",
    "G",
    "S",
    "",
    "+",
    "",
    "",
    "A",
    "",
    "",
    "",
    "",
    "",
    "",
    "A",
    "",
    "",
    "S",
    "",
    "",
    "N",
    "",
    "",
    "",
    "A",
    "-",
    "H",
    "A",
    "",
    "",
    "E",
    "",
    "",
    "D",
    "",
    "",
    "",
    "",
    "",
    "",
    "R",
    "",
    "",
    "N",
    "",
    "",
    "",
    "",
    "",
    "",
    "",
    "",
    "",
    "D",
    "",
    "",
    "T",
    "",
    "",
    "",
    "",
    "",
    "",
    "",
    "",
    "",
    "",
    "C",
    "",
    "I",
    "",
    "",
    "",
    "",
    "",
    "",
    "",
    "",
    "",
    "",
    "O",
    "",
    "M",
    "",
    "",
    "",
    "",
    "",
    "",
    "",
    "F",
    "I",
    "O",
    "R",
    "D",
    "E",
    "S",
    "",
    "",
    "",
    "",
    "",
    "",
    "",
    "",
    "",
    "O",
    "",
    "N",
    "",
    "",
    "",
    "",
    "",
    "",
    "",
    "",
    "",
    "",
    "A",
    "",
    "T",
    "",
    "",
    "",
    "",
    "",
    "",
    "",
    "",
    "",
    "",
    "",
    "",
    "A",
    "",
    "",
    "",
    "",
    "",
    "",
    "",
    "",
    "",
    "",
    "O",
    "S",
    "L",
    "O"
  ],
  "words": [
    {
      "word": "VALOR SENTIMENTAL",
      "positions": [
        11,
        24,
        37,
        50,
        63,
        89,
        102,
        115,
        128,
        141,
        154,
        167,
        180,
        193,
        206,
        219
      ]
    },
    {
      "word": "PAÍS NÓRDICO",
      "positions": [
        39,
        40,
        41,
        42,
        44,
        45,
        46,
        47,
        48,
        49,
        50
      ]
    },
    {
      "word": "ODEGAARD",
      "positions": [
        34,
        47,
        60,
        73,
        86,
        99,
        112,
        125
      ]
    },
    {
      "word": "HAALAND",
      "positions": [
        27,
        40,
        53,
        66,
        79,
        92,
        105
      ]
    },
    {
      "word": "FIORDES",
      "positions": [
        162,
        163,
        164,
        165,
        166,
        167,
        168
      ]
    },
    {
      "word": "VIKINGS",
      "positions": [
        68,
        69,
        70,
        71,
        72,
        73,
        74
      ]
    },
    {
      "word": "COROA",
      "positions": [
        139,
        152,
        165,
        178,
        191
      ]
    },
    {
      "word": "A-HA",
      "positions": [
        96,
        97,
        98,
        99
      ]
    },
    {
      "word": "OSLO",
      "positions": [
        217,
        218,
        219,
        220
      ]
    }
  ]
}