{
  "id": 266,
  "versao": 1,
  "data": "2026-05-28",
  "dificuldade": "Easy",
  "tema": "Spider-Noir",
  "cols": 13,
  "rows": 15,
  "grid": [
    "",
    "",
    "",
    "",
    "",
    "",
    "P",
    "",
    "B",
    "",
    "T",
    "",
    "",
    "",
    "",
    "",
    "",
    "",
    "",
    "R",
    "",
    "L",
    "",
    "H",
    "",
    "",
    "I",
    "N",
    "V",
    "E",
    "S",
    "T",
    "I",
    "G",
    "A",
    "T",
    "I",
    "O",
    "N",
    "",
    "I",
    "",
    "",
    "P",
    "",
    "M",
    "",
    "C",
    "",
    "R",
    "",
    "O",
    "",
    "C",
    "",
    "",
    "I",
    "",
    "E",
    "",
    "K",
    "",
    "T",
    "",
    "I",
    "",
    "O",
    "",
    "",
    "D",
    "",
    "+",
    "",
    "+",
    "",
    "I",
    "",
    "R",
    "",
    "L",
    "",
    "",
    "E",
    "",
    "V",
    "",
    "A",
    "",
    "E",
    "",
    "",
    "",
    "A",
    "",
    "",
    "R",
    "",
    "I",
    "",
    "N",
    "",
    "S",
    "",
    "",
    "",
    "S",
    "",
    "",
    "-",
    "",
    "D",
    "",
    "D",
    "",
    "",
    "",
    "",
    "",
    "+",
    "",
    "",
    "M",
    "",
    "E",
    "",
    "+",
    "",
    "",
    "",
    "",
    "",
    "C",
    "",
    "",
    "A",
    "",
    "O",
    "",
    "W",
    "",
    "",
    "",
    "",
    "",
    "A",
    "",
    "",
    "N",
    "",
    "",
    "",
    "H",
    "",
    "",
    "",
    "",
    "",
    "G",
    "",
    "",
    "",
    "",
    "",
    "",
    "I",
    "",
    "",
    "",
    "",
    "",
    "E",
    "",
    "D",
    "E",
    "T",
    "E",
    "C",
    "T",
    "I",
    "V",
    "E",
    "",
    "",
    "",
    "",
    "",
    "",
    "",
    "",
    "",
    "E",
    "",
    "",
    "",
    ""
  ],
  "words": [
    {
      "word": "BLACK AND WHITE",
      "positions": [
        8,
        21,
        34,
        47,
        60,
        86,
        99,
        112,
        138,
        151,
        164,
        177,
        190
      ]
    },
    {
      "word": "INVESTIGATION",
      "positions": [
        26,
        27,
        28,
        29,
        30,
        31,
        32,
        33,
        34,
        35,
        36,
        37,
        38
      ]
    },
    {
      "word": "NICOLAS CAGE",
      "positions": [
        27,
        40,
        53,
        66,
        79,
        92,
        105,
        131,
        144,
        157,
        170
      ]
    },
    {
      "word": "PRIME VIDEO",
      "positions": [
        6,
        19,
        32,
        45,
        58,
        84,
        97,
        110,
        123,
        136
      ]
    },
    {
      "word": "SPIDER-MAN",
      "positions": [
        30,
        43,
        56,
        69,
        82,
        95,
        108,
        121,
        134,
        147
      ]
    },
    {
      "word": "DETECTIVE",
      "positions": [
        172,
        173,
        174,
        175,
        176,
        177,
        178,
        179,
        180
      ]
    },
    {
      "word": "THIRTIES",
      "positions": [
        10,
        23,
        36,
        49,
        62,
        75,
        88,
        101
      ]
    },
    {
      "word": "NOIR",
      "positions": [
        38,
        51,
        64,
        77
      ]
    }
  ]
}