{
  "id": 43,
  "versao": 1,
  "data": "2025-10-17",
  "dificuldade": "Hard",
  "tema": "Artists in the São Paulo Museum of Art (MASP) collection",
  "cols": 13,
  "rows": 14,
  "grid": [
    "",
    "",
    "",
    "",
    "",
    "V",
    "A",
    "N",
    "+",
    "G",
    "O",
    "G",
    "H",
    "",
    "",
    "",
    "",
    "",
    "",
    "N",
    "",
    "",
    "",
    "",
    "",
    "",
    "",
    "",
    "",
    "",
    "",
    "",
    "I",
    "N",
    "G",
    "R",
    "E",
    "S",
    "",
    "",
    "",
    "M",
    "O",
    "N",
    "E",
    "T",
    "",
    "",
    "",
    "",
    "",
    "",
    "",
    "",
    "",
    "",
    "",
    "",
    "A",
    "",
    "",
    "",
    "",
    "P",
    "",
    "",
    "",
    "",
    "",
    "",
    "",
    "+",
    "",
    "",
    "",
    "",
    "O",
    "",
    "",
    "P",
    "",
    "",
    "",
    "",
    "M",
    "",
    "",
    "R",
    "",
    "R",
    "",
    "D",
    "I",
    "+",
    "C",
    "A",
    "V",
    "A",
    "L",
    "C",
    "A",
    "N",
    "T",
    "I",
    "",
    "C",
    "",
    "É",
    "",
    "",
    "L",
    "",
    "",
    "F",
    "",
    "I",
    "",
    "",
    "A",
    "",
    "Z",
    "",
    "",
    "F",
    "",
    "",
    "A",
    "",
    "N",
    "",
    "",
    "S",
    "",
    "A",
    "",
    "",
    "A",
    "",
    "",
    "E",
    "",
    "A",
    "",
    "",
    "S",
    "",
    "N",
    "",
    "",
    "T",
    "",
    "",
    "L",
    "",
    "R",
    "",
    "",
    "O",
    "",
    "N",
    "",
    "",
    "T",
    "",
    "",
    "",
    "",
    "I",
    "",
    "",
    "",
    "R",
    "E",
    "N",
    "O",
    "I",
    "R",
    "",
    "",
    "",
    "",
    ""
  ],
  "words": [
    {
      "word": "ANITA MALFATTI",
      "positions": [
        6,
        19,
        32,
        45,
        58,
        84,
        97,
        110,
        123,
        136,
        149,
        162,
        175
      ]
    },
    {
      "word": "VAN GOGH",
      "positions": [
        5,
        6,
        7,
        9,
        10,
        11,
        12
      ]
    },
    {
      "word": "INGRES",
      "positions": [
        32,
        33,
        34,
        35,
        36,
        37
      ]
    },
    {
      "word": "MONET",
      "positions": [
        41,
        42,
        43,
        44,
        45
      ]
    },
    {
      "word": "PORTINARI",
      "positions": [
        63,
        76,
        89,
        102,
        115,
        128,
        141,
        154,
        167
      ]
    },
    {
      "word": "DI CAVALCANTI",
      "positions": [
        91,
        92,
        94,
        95,
        96,
        97,
        98,
        99,
        100,
        101,
        102,
        103
      ]
    },
    {
      "word": "RAFAEL",
      "positions": [
        87,
        100,
        113,
        126,
        139,
        152
      ]
    },
    {
      "word": "CÉZANNE",
      "positions": [
        94,
        107,
        120,
        133,
        146,
        159,
        172
      ]
    },
    {
      "word": "PICASSO",
      "positions": [
        79,
        92,
        105,
        118,
        131,
        144,
        157
      ]
    },
    {
      "word": "RENOIR",
      "positions": [
        171,
        172,
        173,
        174,
        175,
        176
      ]
    }
  ]
}